src/math-basics/BasicMath.py
src/math-basics/__init__.py
math_basics-0.0.1.dist-info/METADATA
math_basics-0.0.1.dist-info/WHEEL
math_basics-0.0.1.dist-info/licenses/LICENSE
math_basics-0.0.1.dist-info/RECORD
